ipfs_dict_chain/CID.py
ipfs_dict_chain/IPFS.py
ipfs_dict_chain/IPFSDict.py
ipfs_dict_chain/IPFSDictChain.py
ipfs_dict_chain/__init__.py
ipfs_dict_chain-1.1.0.dist-info/LICENSE
ipfs_dict_chain-1.1.0.dist-info/METADATA
ipfs_dict_chain-1.1.0.dist-info/WHEEL
ipfs_dict_chain-1.1.0.dist-info/top_level.txt
ipfs_dict_chain-1.1.0.dist-info/RECORD
