Metadata-Version: 2.2
Name: ipfs_dict_chain
Version: 1.1.0
Summary: A Python package that provides IPFSDict and IPFSDictChain objects, which are dictionary-like data structures that store their state on IPFS and keep track of changes.
Home-page: https://github.com/ValyrianTech/ipfs_dict_chain
Author: Wouter Glorieux
Author-email: info@valyrian.tech
Classifier: Development Status :: 5 - Production/Stable
Classifier: Intended Audience :: Developers
Classifier: License :: OSI Approved :: MIT License
Classifier: Programming Language :: Python :: 3.10
Classifier: Programming Language :: Python :: 3.11
Classifier: Programming Language :: Python :: 3.12
Requires-Python: >=3.10
License-File: LICENSE
Requires-Dist: aioipfs>=0.7.1
Requires-Dist: multiaddr>=0.0.9
Provides-Extra: dev
Requires-Dist: pytest>=7.4.0; extra == "dev"
Requires-Dist: pytest-cov>=4.1.0; extra == "dev"
Dynamic: author
Dynamic: author-email
Dynamic: classifier
Dynamic: description
Dynamic: description-content-type
Dynamic: home-page
Dynamic: provides-extra
Dynamic: requires-dist
Dynamic: requires-python
Dynamic: summary
